LabJackPython.py
Modbus.py
u12.py
u3.py
u6.py
ue9.py
sti_LabJackPython-2.0.0.post1.dist-info/LICENSE
sti_LabJackPython-2.0.0.post1.dist-info/LICENSE.txt
sti_LabJackPython-2.0.0.post1.dist-info/METADATA
sti_LabJackPython-2.0.0.post1.dist-info/WHEEL
sti_LabJackPython-2.0.0.post1.dist-info/top_level.txt
sti_LabJackPython-2.0.0.post1.dist-info/RECORD
